{
    "data_dir": "data/before_augmentation",
    "targets_json": "configs/targets.json",
    "composite_num": 2,
    "polynomial_model": 1,
    "polynomial_max_order": 1,
    "cutoff_radius_min": 6.0,
    "cutoff_radius_max": 10.0,
    "gaussian_params2_flag": 2,
    "gaussian_params2_num_max": 20,
    "feature_type": "gtinv",
    "gtinv_lmax": [
        9,
        7,
        3,
        2,
        2
    ],
    "use_gtinv_sym": false,
    "use_spin": false,
    "use_force": true,
    "shuffle": true,
    "use_cache_to_split_data": true,
    "alpha": [
        0.01,
        0.001
    ],
    "n_splits": 5,
    "save_log": true,
    "model_dir": "models",
    "n_jobs": -1
}
